README.md
setup.cfg
setup.py
statspark/__init__.py
statspark/r_inspired.py
statspark/tests.py
statspark.egg-info/PKG-INFO
statspark.egg-info/SOURCES.txt
statspark.egg-info/dependency_links.txt
statspark.egg-info/requires.txt
statspark.egg-info/top_level.txt
statspark/config/__init__.py
statspark/config/config.py
statspark/qgf/__init__.py
statspark/qgf/qgf.py